README.md
setup.py
headerinjection/main.py
headerinjection/includes/__init__.py
headerinjection/includes/file.py
headerinjection/includes/scan.py
headerinjection/includes/sms.py
headerinjection/includes/write.py
headerinjection/units/__init__.py
headerinjection/units/banner.py
headerinjection/units/chknet.py
headerinjection/units/url.py
hostinjection.egg-info/PKG-INFO
hostinjection.egg-info/SOURCES.txt
hostinjection.egg-info/dependency_links.txt
hostinjection.egg-info/entry_points.txt
hostinjection.egg-info/requires.txt
hostinjection.egg-info/top_level.txt